README.txt
setup.cfg
setup.py
docs/HISTORY.txt
docs/INSTALL.txt
docs/LICENSE.GPL
docs/LICENSE.txt
easyshop/__init__.py
easyshop.discounts.egg-info/PKG-INFO
easyshop.discounts.egg-info/SOURCES.txt
easyshop.discounts.egg-info/dependency_links.txt
easyshop.discounts.egg-info/entry_points.txt
easyshop.discounts.egg-info/namespace_packages.txt
easyshop.discounts.egg-info/not-zip-safe
easyshop.discounts.egg-info/requires.txt
easyshop.discounts.egg-info/top_level.txt
easyshop/discounts/__init__.py
easyshop/discounts/configure.zcml
easyshop/discounts/profiles.zcml
easyshop/discounts/tests.py
easyshop/discounts/adapters/__init__.py
easyshop/discounts/adapters/configure.zcml
easyshop/discounts/adapters/discounts_management.py
easyshop/discounts/adapters/prices.py
easyshop/discounts/browser/__init__.py
easyshop/discounts/browser/configure.zcml
easyshop/discounts/browser/discount.pt
easyshop/discounts/browser/discount.py
easyshop/discounts/browser/discounts_container.pt
easyshop/discounts/browser/discounts_container.py
easyshop/discounts/content/__init__.py
easyshop/discounts/content/discount.py
easyshop/discounts/content/discounts_container.py
easyshop/discounts/profiles/default/factorytool.xml
easyshop/discounts/profiles/default/types.xml
easyshop/discounts/profiles/default/workflows.xml
easyshop/discounts/profiles/default/types/Discount.xml
easyshop/discounts/profiles/default/types/DiscountsContainer.xml